setup.cfg
setup.py
marshest/__init__.py
marshest/marshclients.py
marshest/marshmodels.py
marshest.egg-info/PKG-INFO
marshest.egg-info/SOURCES.txt
marshest.egg-info/dependency_links.txt
marshest.egg-info/requires.txt
marshest.egg-info/top_level.txt