Metadata-Version: 1.1
Name: marshest
Version: 0.1
Summary: A library for Marshalling JSON requests
Home-page: https://github.com/jaydeepc/marshmallow
Author: Jaydeep Chakrabarty
Author-email: jaydeepc@thoughtworks.com
License: UNKNOWN
Download-URL: https://github.com/jaydeepc/marshmallow/tarball/0.1
Keywords: testing,marshalling,json,restapi,api,automation,functionaltesting
Platform: UNKNOWN
